LICENSE
MANIFEST.in
README.rst
buildout.cfg
develop.cfg
pyproject.toml
requirements.txt
setup.py
version.txt
bob/__init__.py
bob.blitz.egg-info/PKG-INFO
bob.blitz.egg-info/SOURCES.txt
bob.blitz.egg-info/dependency_links.txt
bob.blitz.egg-info/not-zip-safe
bob.blitz.egg-info/requires.txt
bob.blitz.egg-info/top_level.txt
bob/blitz/__init__.py
bob/blitz/api.cpp
bob/blitz/array.cpp
bob/blitz/extension.py
bob/blitz/main.cpp
bob/blitz/notest_extensions.py
bob/blitz/test.py
bob/blitz/version.cpp
bob/blitz/examples/bob.example.extension/MANIFEST.in
bob/blitz/examples/bob.example.extension/README.rst
bob/blitz/examples/bob.example.extension/buildout.cfg
bob/blitz/examples/bob.example.extension/pyproject.toml
bob/blitz/examples/bob.example.extension/requirements.txt
bob/blitz/examples/bob.example.extension/setup.py
bob/blitz/examples/bob.example.extension/version.txt
bob/blitz/examples/bob.example.extension/bob/__init__.py
bob/blitz/examples/bob.example.extension/bob/example/__init__.py
bob/blitz/examples/bob.example.extension/bob/example/extension/Function.cpp
bob/blitz/examples/bob.example.extension/bob/example/extension/__init__.py
bob/blitz/examples/bob.example.extension/bob/example/extension/main.cpp
bob/blitz/examples/bob.example.extension/bob/example/extension/test.py
bob/blitz/examples/bob.example.extension/bob/example/extension/version.cpp
bob/blitz/examples/bob.example.extension/bob/example/extension/script/__init__.py
bob/blitz/examples/bob.example.extension/bob/example/extension/script/reverse.py
bob/blitz/examples/bob.example.extension/bob/example/extension/script/version.py
bob/blitz/examples/bob.example.extension/doc/conf.py
bob/blitz/examples/bob.example.extension/doc/index.rst
bob/blitz/examples/bob.example.extension/doc/img/favicon.ico
bob/blitz/examples/bob.example.extension/doc/img/logo.png
bob/blitz/examples/bob.example.library/MANIFEST.in
bob/blitz/examples/bob.example.library/README.rst
bob/blitz/examples/bob.example.library/buildout.cfg
bob/blitz/examples/bob.example.library/pyproject.toml
bob/blitz/examples/bob.example.library/requirements.txt
bob/blitz/examples/bob.example.library/setup.py
bob/blitz/examples/bob.example.library/version.txt
